calculator.py
poetry_publish_pypi-0.1.0.dist-info/METADATA
poetry_publish_pypi-0.1.0.dist-info/WHEEL
poetry_publish_pypi-0.1.0.dist-info/RECORD
