Metadata-Version: 2.1
Name: poetry-publish-pypi
Version: 0.1.0
Summary: 
Author: mahfooz.iiitian
Author-email: mahfooz.iiitian@gmail.com
Requires-Python: >=3.10,<4.0
Classifier: Programming Language :: Python :: 3
Classifier: Programming Language :: Python :: 3.10
Classifier: Programming Language :: Python :: 3.11
Classifier: Programming Language :: Python :: 3.12
Requires-Dist: requests (>=2.31.0,<3.0.0)
